HABSlib/__init__.py
HABSlib/board_manager.py
HABSlib/config.py
HABSlib/crypt.py
HABSlib/metadata.json
HABSlib/service.py
HABSlib/utils.py
HABSlib-0.1.64.data/data/docs/index.html
tests/__init__.py
tests/config.py
tests/conftest.py
tests/test_ghost.py
tests/test_habslib.py
tests/test_openbci.py
tests/test_pipe.py
tests/test_process_session_pipe.py
tests/test_raw.py
tests/test_send_file.py
tests/test_service.py
tests/test_tagging_existing_data.py
HABSlib-0.1.64.dist-info/LICENCE
HABSlib-0.1.64.dist-info/METADATA
HABSlib-0.1.64.dist-info/WHEEL
HABSlib-0.1.64.dist-info/top_level.txt
HABSlib-0.1.64.dist-info/RECORD
