Metadata-Version: 2.1
Name: HABSlib
Version: 0.1.64
Summary: A library for interacting with the HABS CognitiveOS API.
Home-page: https://github.com/Olocufier/HABS.git
Author: Domenico Guarino
Author-email: domenico@habs.ai
License: MIT
Classifier: Programming Language :: Python :: 3
Classifier: License :: OSI Approved :: MIT License
Classifier: Operating System :: OS Independent
Requires-Python: >=3.6
License-File: LICENCE
Requires-Dist: asyncio ==3.4.3
Requires-Dist: brainflow ==5.12.1
Requires-Dist: numpy ==1.26.4
Requires-Dist: requests ==2.31.0
Requires-Dist: urllib3 ==2.2.1
Requires-Dist: jsonschema
Requires-Dist: rfc3339-validator
Requires-Dist: scipy
Requires-Dist: pytest
Requires-Dist: pytest-html
Requires-Dist: pytest-order
Requires-Dist: pytest-dependency
Requires-Dist: pdoc
Requires-Dist: pyEDFlib
